acquantumconnector/__init__.py
acquantumconnector/_version.py
acquantumconnector/connector/__init__.py
acquantumconnector/connector/acquantumconnector.py
acquantumconnector/credentials/__init__.py
acquantumconnector/credentials/credentials.py
acquantumconnector/model/__init__.py
acquantumconnector/model/backendtype.py
acquantumconnector/model/config.py
acquantumconnector/model/errors.py
acquantumconnector/model/gates.py
acquantumconnector/model/response.py
acquantum_connector-0.0.5.dist-info/LICENSE
acquantum_connector-0.0.5.dist-info/METADATA
acquantum_connector-0.0.5.dist-info/WHEEL
acquantum_connector-0.0.5.dist-info/top_level.txt
acquantum_connector-0.0.5.dist-info/RECORD
