Metadata-Version: 2.1
Name: acquantum-connector
Version: 0.0.5
Summary: UNKNOWN
Home-page: https://github.com/carstenblank/acquantum-connector
Author: Carsten Blank
Author-email: blank@data-cybernetics.com
License: Apache 2.0
Platform: UNKNOWN
Classifier: Development Status :: 4 - Beta
Classifier: Programming Language :: Python :: 3
Classifier: Programming Language :: Python :: 3 :: Only
Classifier: License :: OSI Approved :: Apache Software License
Classifier: Operating System :: OS Independent
Requires-Dist: requests
